ras_common_utils/__init__.py
ras_common_utils/__version__.py
ras_common_utils-1.0.0.dist-info/DESCRIPTION.rst
ras_common_utils-1.0.0.dist-info/METADATA
ras_common_utils-1.0.0.dist-info/RECORD
ras_common_utils-1.0.0.dist-info/WHEEL
ras_common_utils-1.0.0.dist-info/entry_points.txt
ras_common_utils-1.0.0.dist-info/metadata.json
ras_common_utils-1.0.0.dist-info/top_level.txt
