Metadata-Version: 2.0
Name: ras-common-utils
Version: 1.0.0
Summary: A common library for RAS utilities
Home-page: https://github.com/ONSdigital/ras-common-utils
Author: G Irving
Author-email: gemma.i_95@hotmail.co.uk
License: UNKNOWN
Platform: UNKNOWN
Classifier: Programming Language :: Python :: 3.6
Classifier: License :: OSI Approved :: MIT License
Requires-Dist: Flask (==0.12.2)
Requires-Dist: PyYAML (==3.12)
Requires-Dist: SQLAlchemy (==1.1.10)
Requires-Dist: structlog (==17.2.0)
